pre_layout/vsdserializer_v1.v
module vsdserializer_v1(clk, load, INPUT, OUTPUT);
input clk, load;
input [9:0] INPUT;
output reg OUTPUT;
reg [9:0] tmp;
always @(posedge clk)
begin
  if(load)
  tmp<=INPUT;
  else
  begin
  OUTPUT <= tmp[9];
  tmp <= {tmp[8:0],1'b0};
  end
end
endmodule

vsdserializer_v1_tb.v
`timescale 1ns / 1ps
`include "vsdserializer_v1.v"
module vsdserializer_v1_tb();
reg clk,load;
reg[9:0] INPUT;
wire OUTPUT;
vsdserializer_v1 dut (clk, load, INPUT, OUTPUT);
initial begin
 clk = 1;
 INPUT = $urandom;
 load = 1;
 #30 load = 0;
 #120 INPUT = $urandom;
load = 1;
#30 load = 0;
#120 INPUT = $urandom;
load = 1;
#30 load = 0;
end
always #50 clk = ~clk;
initial begin
$dumpfile("vsdserializer_v1_tb.vcd");
$dumpvars(0,vsdserializer_v1_tb);
#900 $finish;
end
endmodule

TESTBENCH/vsdserializer_v1_tb.vcd
$date
	Tue Aug 10 16:08:52 2021
$end
$version
	Icarus Verilog
$end
$timescale
	1ps
$end
$scope module vsdserializer_v1_tb $end
$var wire 1 ! OUTPUT $end
$var reg 10 " INPUT [9:0] $end
$var reg 1 # clk $end
$var reg 1 $ load $end
$scope module dut $end
$var wire 10 % INPUT [9:0] $end
$var wire 1 # clk $end
$var wire 1 $ load $end
$var reg 1 ! OUTPUT $end
$var reg 10 & tmp [9:0] $end
$upscope $end
$upscope $end
$enddefinitions $end
#0
$dumpvars
b100100100 &
b100100100 %
1$
1#
b100100100 "
x!
$end
#5000
0#
#10000
1#
#15000
0#
#20000
1#
#25000
0#
#30000
0!
b1001001000 &
1#
0$
#35000
0#
#40000
1!
b10010000 &
1#
#45000
0#
#50000
0!
b100100000 &
1#
#55000
0#
#60000
b1001000000 &
1#
#65000
0#
#70000
1!
b10000000 &
1#
#75000
0#
#80000
0!
b100000000 &
1#
#85000
0#
#90000
b1000000000 &
1#
#95000
0#
#100000
1!
b0 &
1#
#105000
0#
#110000
0!
1#
#115000
0#
#120000
1#
#125000
0#
#130000
1#
#135000
0#
#140000
1#
#145000
0#
#150000
b1010000001 &
1#
1$
b1010000001 "
b1010000001 %
#155000
0#
#160000
1#
#165000
0#
#170000
1#
#175000
0#
#180000
1!
b100000010 &
1#
0$
#185000
0#
#190000
0!
b1000000100 &
1#
#195000
0#
#200000
1!
b1000 &
1#
#205000
0#
#210000
0!
b10000 &
1#
#215000
0#
#220000
b100000 &
1#
#225000
0#
#230000
b1000000 &
1#
#235000
0#
#240000
b10000000 &
1#
#245000
0#
#250000
b100000000 &
1#
#255000
0#
#260000
b1000000000 &
1#
#265000
0#
#270000
1!
b0 &
1#
#275000
0#
#280000
0!
1#
#285000
0#
#290000
1#
#295000
0#
#300000
b1000001001 &
1#
1$
b1000001001 "
b1000001001 %
#305000
0#
#310000
1#
#315000
0#
#320000
1#
#325000
0#
#330000
1!
b10010 &
1#
0$
#335000
0#
#340000
0!
b100100 &
1#
#345000
0#
#350000
b1001000 &
1#
#355000
0#
#360000
b10010000 &
1#
#365000
0#
#370000
b100100000 &
1#
#375000
0#
#380000
b1001000000 &
1#
#385000
0#
#390000
1!
b10000000 &
1#
#395000
0#
#400000
0!
b100000000 &
1#
#405000
0#
#410000
b1000000000 &
1#
#415000
0#
#420000
1!
b0 &
1#
#425000
0#
#430000
0!
1#
